setup.py
NorBi_distribution/Binomialdistribution.py
NorBi_distribution/Gaussiandistribution.py
NorBi_distribution/Generaldistribution.py
NorBi_distribution/__init__.py
NorBi_distribution.egg-info/PKG-INFO
NorBi_distribution.egg-info/SOURCES.txt
NorBi_distribution.egg-info/dependency_links.txt
NorBi_distribution.egg-info/not-zip-safe
NorBi_distribution.egg-info/top_level.txt