Metadata-Version: 1.0
Name: NorBi-distribution
Version: 1.10
Summary: Gaussian and Binomial distributions
Home-page: UNKNOWN
Author: Nneamaka chalokwu
Author-email: chalokwun@gmail.com
License: UNKNOWN
Platform: UNKNOWN
